easyxlwings/__init__.py
easyxlwings/__main__.py
easyxlwings/excel2json.py
easyxlwings/utils.py
easyxlwings-1.0.14.dist-info/LICENSE
easyxlwings-1.0.14.dist-info/METADATA
easyxlwings-1.0.14.dist-info/WHEEL
easyxlwings-1.0.14.dist-info/top_level.txt
easyxlwings-1.0.14.dist-info/RECORD
