Metadata-Version: 2.1
Name: easyxlwings
Version: 1.0.14
Summary: UNKNOWN
Home-page: https://github.com/leeheisen/easyxlwings
Author: leeheisen
License: UNKNOWN
Platform: UNKNOWN
Classifier: Programming Language :: Python :: 3
Classifier: License :: OSI Approved :: MIT License
Classifier: Operating System :: OS Independent
Requires-Python: >=3.8
Requires-Dist: xlwings
Requires-Dist: json5
